{
    "_config_name": "nivo_slider.settings",
    "nivo_slider_effect": "random",
    "nivo_slider_image_style": 0,
    "nivo_slider_image_style_slide": "large",
    "nivo_slider_image_style_thumb": "thumbnail",
    "nivo_slider_slices": "15",
    "nivo_slider_box_columns": "8",
    "nivo_slider_box_rows": "4",
    "nivo_slider_animation_speed": "500",
    "nivo_slider_pause_time": "3000",
    "nivo_slider_start_slide": "0",
    "nivo_slider_directional_navigation": 1,
    "nivo_slider_control_navigation": 1,
    "nivo_slider_control_nav_thumbs": 0,
    "nivo_slider_pause_on_hover": 1,
    "nivo_slider_manual_advance": 0,
    "nivo_slider_previous_text": "Prev",
    "nivo_slider_next_text": "Next",
    "nivo_slider_random_start": 0,
    "nivo_slider_theme": "default",
    "nivo_slider_banner_settings": [],
    "nivo_slider_banner_html_captions": ""
}
